conf/__init__.py
conf/config.yaml
conf/__pycache__/__init__.cpython-310.pyc
conf/app/__init__.py
conf/app/gui.yaml
conf/lsystem/__init__.py
conf/lsystem/dragon_curve.yaml
conf/lsystem/hexagonal_gosper_curve.yaml
conf/lsystem/plant_edge_rewriting_1.yaml
conf/lsystem/plant_edge_rewriting_2.yaml
conf/lsystem/plant_node_rewriting_1.yaml
conf/lsystem/plant_node_rewriting_2.yaml
conf/lsystem/quadratic_koch_island.yaml
conf/lsystem/sierpinsky_triangle.yaml
conf/lsystem/squared_squares.yaml
conf/lsystem/stochastic_plant_edge_rewriting.yaml
lsystem/__init__.py
lsystem/config.py
lsystem/derivator.py
lsystem/mapping.py
lsystem/renderer.py
lsystem/__pycache__/__init__.cpython-310.pyc
lsystem/__pycache__/config.cpython-310.pyc
lsystem/__pycache__/derivation.cpython-310.pyc
lsystem/__pycache__/derivator.cpython-310.pyc
lsystem/__pycache__/lsystem.cpython-310.pyc
lsystem/__pycache__/mapping.cpython-310.pyc
lsystem/__pycache__/renderer.cpython-310.pyc
lsystem/__pycache__/state.cpython-310.pyc
lsystem/model/__init__.py
lsystem/model/alphabet.py
lsystem/model/grammar.py
lsystem/model/rule.py
lsystem/model/ruleset.py
lsystem/model/symbol.py
lsystem/model/word.py
lsystem/model/__pycache__/__init__.cpython-310.pyc
lsystem/model/__pycache__/alphabet.cpython-310.pyc
lsystem/model/__pycache__/grammar.cpython-310.pyc
lsystem/model/__pycache__/rule.cpython-310.pyc
lsystem/model/__pycache__/ruleset.cpython-310.pyc
lsystem/model/__pycache__/symbol.cpython-310.pyc
lsystem/model/__pycache__/word.cpython-310.pyc
scripts/__init__.py
scripts/gui.py
test/__init__.py
test/lsystem_test.py
test/common/__init__.py
test/common/instruction_enum_test.py
test/model/__init__.py
test/model/alphabet_test.py
test/model/grammar_test.py
test/model/rule_test.py
test/model/ruleset_test.py
test/model/symbol_test.py
test/model/word_test.py
LSystemRenderer-0.0.9.dist-info/LICENCE
LSystemRenderer-0.0.9.dist-info/METADATA
LSystemRenderer-0.0.9.dist-info/WHEEL
LSystemRenderer-0.0.9.dist-info/entry_points.txt
LSystemRenderer-0.0.9.dist-info/top_level.txt
LSystemRenderer-0.0.9.dist-info/RECORD
