Metadata-Version: 2.1
Name: LSystemRenderer
Version: 0.0.9
Summary: Display images generated by L-Systems.
Home-page: https://github.com/A-Bak/l-system
Author: A-Bak
Author-email: adam.bak.work@gmail.com
License: UNKNOWN
Keywords: l-system generative-art image-generation grammar renderer
Platform: UNKNOWN
Classifier: Programming Language :: Python :: 3
Classifier: License :: OSI Approved :: MIT License
Classifier: Operating System :: OS Independent
Requires-Python: >=3.6
License-File: LICENCE
Requires-Dist: antlr4-python3-runtime (==4.9.3)
Requires-Dist: black (==22.10.0)
Requires-Dist: bleach (==5.0.1)
Requires-Dist: certifi (==2022.9.24)
Requires-Dist: charset-normalizer (==2.1.1)
Requires-Dist: click (==8.1.3)
Requires-Dist: colorama (==0.4.5)
Requires-Dist: commonmark (==0.9.1)
Requires-Dist: docutils (==0.19)
Requires-Dist: hydra-core (==1.2.0)
Requires-Dist: idna (==3.4)
Requires-Dist: importlib-metadata (==5.0.0)
Requires-Dist: jaraco.classes (==3.2.3)
Requires-Dist: keyring (==23.9.3)
Requires-Dist: more-itertools (==8.14.0)
Requires-Dist: mypy-extensions (==0.4.3)
Requires-Dist: omegaconf (==2.2.3)
Requires-Dist: packaging (==21.3)
Requires-Dist: pathspec (==0.10.1)
Requires-Dist: pkginfo (==1.8.3)
Requires-Dist: platformdirs (==2.5.2)
Requires-Dist: Pygments (==2.13.0)
Requires-Dist: pyparsing (==3.0.9)
Requires-Dist: pywin32-ctypes (==0.2.0)
Requires-Dist: PyYAML (==6.0)
Requires-Dist: readme-renderer (==37.2)
Requires-Dist: requests (==2.28.1)
Requires-Dist: requests-toolbelt (==0.10.0)
Requires-Dist: rfc3986 (==2.0.0)
Requires-Dist: rich (==12.6.0)
Requires-Dist: six (==1.16.0)
Requires-Dist: tomli (==2.0.1)
Requires-Dist: twine (==4.0.1)
Requires-Dist: urllib3 (==1.26.12)
Requires-Dist: webencodings (==0.5.1)
Requires-Dist: zipp (==3.9.0)
